Metadata-Version: 2.1
Name: FixedFloatApi
Version: 1.0.3
Summary: Python wrapper for interacting with the FixedFloat API to exchange cryptocurrencies.
Home-page: https://github.com/Jobians/FixedFloatApi-Python
Author: JobiansTechie
Author-email: jobianstechie@gmail.com
License: MIT
Keywords: FixedFloat,Api,FixedFloat Python
Platform: UNKNOWN
Classifier: Development Status :: 3 - Alpha
Classifier: Intended Audience :: Developers
Classifier: License :: OSI Approved :: MIT License
Classifier: Programming Language :: Python :: 3
Classifier: Programming Language :: Python :: 3.6
Classifier: Programming Language :: Python :: 3.7
Classifier: Programming Language :: Python :: 3.8
Classifier: Programming Language :: Python :: 3.9
